LICENSE
MANIFEST.in
README.md
setup.py
docums_exclude/__init__.py
docums_exclude/plugin.py
docums_exclude.egg-info/PKG-INFO
docums_exclude.egg-info/SOURCES.txt
docums_exclude.egg-info/dependency_links.txt
docums_exclude.egg-info/entry_points.txt
docums_exclude.egg-info/requires.txt
docums_exclude.egg-info/top_level.txt