Metadata-Version: 2.1
Name: docums-exclude
Version: 1.0.2
Summary: A docums plugin that lets you exclude files or trees.
Home-page: https://github.com/khanhduy1407/docums-exclude
Author: NKDuy
Author-email: kn145660@gmail.com
License: Apache
Platform: UNKNOWN
